icalendar_compatibility/.gitignore
icalendar_compatibility/__init__.py
icalendar_compatibility/_version.py
icalendar_compatibility/description.py
icalendar_compatibility/location.py
icalendar_compatibility/version.py
icalendar_compatibility/test/__init__.py
icalendar_compatibility/test/conftest.py
icalendar_compatibility/test/test_description.py
icalendar_compatibility/test/test_location.py
icalendar_compatibility/test/test_with_doctest.py
icalendar_compatibility/test/events/description_altrep_html.ics
icalendar_compatibility/test/events/description_html.ics
icalendar_compatibility/test/events/location_altrep.ics
icalendar_compatibility/test/events/location_geo.ics
icalendar_compatibility/test/events/location_geo_misplaced.ics
icalendar_compatibility/test/events/location_link.ics
icalendar_compatibility/test/events/location_text.ics
icalendar_compatibility/test/events/no_description.ics
icalendar_compatibility/test/events/no_location.ics
icalendar_compatibility/test/events/x_alt_description.ics
icalendar_compatibility-0.1.4.dist-info/METADATA
icalendar_compatibility-0.1.4.dist-info/WHEEL
icalendar_compatibility-0.1.4.dist-info/licenses/LICENSE
icalendar_compatibility-0.1.4.dist-info/RECORD
