Metadata-Version: 2.4
Name: icalendar_compatibility
Version: 0.1.4
Summary: ICalendar event information with maximum compatibility to various ICS sources.
Project-URL: Homepage, https://icalendar-compatibility.readthedocs.io/
Project-URL: Repository, https://github.com/niccokunzmann/icalendar_compatibility/
Project-URL: source_archive, https://github.com/niccokunzmann/icalendar_compatibility/archive/c9a8f1eec08a4bfef858e209f0f941ebf97abb4c.zip
Project-URL: Issues, https://github.com/niccokunzmann/icalendar_compatibility/issues
Project-URL: Documentation, https://icalendar-compatibility.readthedocs.io/
Project-URL: Changelog, https://icalendar-compatibility.readthedocs.io/en/latest/changes.html
Author-email: Nicco Kunzmann <niccokunzmann@rambler.ru>
Maintainer-email: Nicco Kunzmann <niccokunzmann@rambler.ru>
License: 
License-File: LICENSE
Keywords: calendar,icalendar,ics,rfc5545
Classifier: Development Status :: 4 - Beta
Classifier: Intended Audience :: Developers
Classifier: License :: OSI Approved :: GNU General Public License v2 or later (GPLv2+)
Classifier: Operating System :: OS Independent
Classifier: Programming Language :: Python :: 3
Classifier: Topic :: Office/Business :: Scheduling
Requires-Python: >=3.9
Requires-Dist: icalendar
Provides-Extra: dev
Requires-Dist: pytest; extra == 'dev'
Provides-Extra: docs
Requires-Dist: sphinx; extra == 'docs'
Requires-Dist: sphinx-copybutton; extra == 'docs'
Requires-Dist: sphinx-rtd-theme; extra == 'docs'
